soneti/__init__.py
soneti/tasks.py
soneti/__pycache__/__init__.cpython-37.pyc
soneti/cron/__init__.py
soneti/cron/__main__.py
soneti/cron/__pycache__/__init__.cpython-37.pyc
soneti/cron/__pycache__/__main__.cpython-37.pyc
soneti-0.1.6.dist-info/LICENSE
soneti-0.1.6.dist-info/METADATA
soneti-0.1.6.dist-info/WHEEL
soneti-0.1.6.dist-info/top_level.txt
soneti-0.1.6.dist-info/RECORD
