Metadata-Version: 2.1
Name: soneti
Version: 0.1.6
Summary: Luigi Tasks for Soneti Orchestration
Home-page: https://lab.gsi.upm.es/social/soneti
Author: Grupo de Sistemas Inteligentes
Author-email: lab-gsi@dit.upm.es
License: UNKNOWN
Platform: UNKNOWN
Requires-Dist: luigi
Requires-Dist: sqlalchemy
Requires-Dist: requests
Requires-Dist: elasticsearch
